pysnarl/__init__.py
pysnarl/__main__.py
pysnarl/snarl.py
pysnarl-0.33.data/data/LICENSE.md
pysnarl-0.33.data/data/README.md
pysnarl-0.33.data/data/__version__.py
pysnarl-0.33.dist-info/LICENSE.md
pysnarl-0.33.dist-info/METADATA
pysnarl-0.33.dist-info/WHEEL
pysnarl-0.33.dist-info/entry_points.txt
pysnarl-0.33.dist-info/top_level.txt
pysnarl-0.33.dist-info/RECORD
