Metadata-Version: 2.1
Name: pysnarl
Version: 0.33
Summary: Snarl python lib, Send SNP/3.1 messages. (Snarl)
Home-page: https://github.com/cumulus13/snarl
Author: Hadi Cahyadi LD
Author-email: cumulus13@gmail.com
Maintainer: cumulus13 Team
Maintainer-email: cumulus13@gmail.com
License: GPL
Project-URL: Documentation, https://github.com/cumulus13/snarl
Project-URL: Code, https://github.com/cumulus13/snarl
Classifier: Development Status :: 5 - Production/Stable
Classifier: Intended Audience :: Developers
Classifier: License :: OSI Approved :: GNU General Public License (GPL)
Classifier: Operating System :: OS Independent
Classifier: Programming Language :: Python
Classifier: Programming Language :: Python :: 3
Requires-Python: >=3
License-File: LICENSE.md
Requires-Dist: argparse
Requires-Dist: rich
Requires-Dist: configset
Requires-Dist: ctraceback
